polygon/__init__.py
polygon/base_client.py
polygon/enums.py
polygon/crypto/__init__.py
polygon/crypto/crypto_api.py
polygon/forex/__init__.py
polygon/forex/forex_api.py
polygon/indices/__init__.py
polygon/indices/indices.py
polygon/options/__init__.py
polygon/options/options.py
polygon/reference_apis/__init__.py
polygon/reference_apis/reference_api.py
polygon/stocks/__init__.py
polygon/stocks/stocks.py
polygon/streaming/__init__.py
polygon/streaming/async_streaming.py
polygon/streaming/constants.py
polygon/streaming/streaming.py
polygon-1.2.5.dist-info/LICENSE
polygon-1.2.5.dist-info/METADATA
polygon-1.2.5.dist-info/WHEEL
polygon-1.2.5.dist-info/top_level.txt
polygon-1.2.5.dist-info/RECORD
