Metadata-Version: 2.1
Name: polygon
Version: 1.2.5
Summary: A Complete Python Wrapper for Polygon.io APIs.
Home-page: https://github.com/pssolanki111/polygon
Author: Pankaj Singh Solanki
Author-email: nice_try@fbi.com
License: MIT
Project-URL: Issue Tracker, https://github.com/pssolanki111/polygon/issues
Project-URL: Discussions, https://github.com/pssolanki111/polygon/discussions
Project-URL: Support, https://www.patreon.com/pssolanki
Keywords: finance trading equities bonds options research data markets
Classifier: Programming Language :: Python :: 3
Classifier: License :: OSI Approved :: MIT License
Classifier: Operating System :: OS Independent
Classifier: Intended Audience :: Developers
Classifier: Development Status :: 5 - Production/Stable
Classifier: Natural Language :: English
Classifier: Topic :: Office/Business :: Financial :: Investment
Requires-Python: >=3.6
License-File: LICENSE
Requires-Dist: requests
Requires-Dist: websockets
Requires-Dist: websocket-client
Requires-Dist: httpx
Provides-Extra: all
Requires-Dist: orjson; extra == "all"
Requires-Dist: uvloop; extra == "all"
Provides-Extra: orjson
Requires-Dist: orjson; extra == "orjson"
Provides-Extra: uvloop
Requires-Dist: uvloop; extra == "uvloop"
